setup.py
bin/pungen
pungen/__init__.py
pungen/main.py
pungen.egg-info/PKG-INFO
pungen.egg-info/SOURCES.txt
pungen.egg-info/dependency_links.txt
pungen.egg-info/top_level.txt